monnik/core.py
monnik/monnik.py
monnik/uri.py
monnik-0.1.0a1.dist-info/LICENSE
monnik-0.1.0a1.dist-info/METADATA
monnik-0.1.0a1.dist-info/WHEEL
monnik-0.1.0a1.dist-info/top_level.txt
monnik-0.1.0a1.dist-info/RECORD
