Metadata-Version: 2.1
Name: monnik
Version: 0.1.0a1
Summary: Library for easy querying of Flanders Heritage REST services.
Home-page: http://github.com/onroerenderfgoed/monnik
Author: Koen Van Daele
Author-email: koen.vandaele@vlaanderen.be
License: MIT
Platform: UNKNOWN
Classifier: Development Status :: 3 - Alpha
Classifier: Intended Audience :: Developers
Classifier: Intended Audience :: Science/Research
Classifier: Topic :: Scientific/Engineering
Classifier: Natural Language :: English
Classifier: License :: OSI Approved :: MIT License
Classifier: Programming Language :: Python
Classifier: Programming Language :: Python :: 3.6
Classifier: Programming Language :: Python :: 3.7
Classifier: Programming Language :: Python :: 3.8
Classifier: Programming Language :: Python :: 3.9
Classifier: Programming Language :: Python :: 3.10
License-File: LICENSE
Requires-Dist: rfc3987
Requires-Dist: requests
